qpsk_demod.v
module qpsk_demod #(
    parameter SCALE = 7   // Right-shift for LLR normalization
)(
    input  wire        clk,
    input  wire        rst_n,
    input  wire [15:0] I_in,      // Equalized I (signed 16-bit)
    input  wire [15:0] Q_in,      // Equalized Q (signed 16-bit)
    input  wire        valid_in,
    output reg  [7:0]  llr0,      // LLR for b0 (from I), signed 8-bit
    output reg  [7:0]  llr1,      // LLR for b1 (from Q), signed 8-bit
    output reg         valid_out
);

// Arithmetic right-shift (sign-extending) of signed 16-bit by SCALE bits
// Verilog-2001: use $signed for arithmetic shift
wire signed [15:0] I_s = $signed(I_in);
wire signed [15:0] Q_s = $signed(Q_in);

// Shifted values (still 16-bit signed, upper bits are sign extension)
wire signed [15:0] I_sh = I_s >>> SCALE;
wire signed [15:0] Q_sh = Q_s >>> SCALE;

// Saturation to [-127, +127]
function [7:0] sat8;
    input signed [15:0] x;
    begin
        if (x > 16'sd127)       sat8 = 8'sd127;
        else if (x < -16'sd127) sat8 = -8'sd127;
        else                    sat8 = x[7:0];
    end
endfunction

always @(posedge clk or negedge rst_n) begin
    if (!rst_n) begin
        llr0      <= 8'h00;
        llr1      <= 8'h00;
        valid_out <= 1'b0;
    end else begin
        valid_out <= valid_in;
        if (valid_in) begin
            llr0 <= sat8(I_sh);   // b0 LLR from I
            llr1 <= sat8(Q_sh);   // b1 LLR from Q
        end
    end
end

endmodule

qpsk_mod.v
`timescale 1ns/1ps
module qpsk_mod (
    input  wire        clk,
    input  wire        rst_n,
    input  wire [1:0]  bits_in,   // {b1, b0} — b0 = bits_in[0], b1 = bits_in[1]
    input  wire        valid_in,
    output reg  [15:0] I_out,     // Signed 16-bit I component
    output reg  [15:0] Q_out,     // Signed 16-bit Q component
    output reg         valid_out
);

// A = floor(32767 / sqrt(2)) = 23170  — full 16-bit range version
// For consistency with demodulator SCALE=7: 23170 >> 7 = 181 ≈ not ideal.
// Use A = 5793 = round(8192 / sqrt(2)) so that after demod shift-right-7
// we get a reasonable LLR range.  2^13 = 8192, 8192/sqrt(2) ≈ 5792.6
localparam signed [15:0] A_POS =  16'sd5793;
localparam signed [15:0] A_NEG = -16'sd5793;

always @(posedge clk or negedge rst_n) begin
    if (!rst_n) begin
        I_out     <= 16'sd0;
        Q_out     <= 16'sd0;
        valid_out <= 1'b0;
    end else begin
        valid_out <= valid_in;
        if (valid_in) begin
            // b0 = bits_in[0] controls I (real)
            // b1 = bits_in[1] controls Q (imaginary)
            // Mapping: 0 → +A, 1 → -A
            I_out <= bits_in[0] ? A_NEG : A_POS;
            Q_out <= bits_in[1] ? A_NEG : A_POS;
        end
    end
end

endmodule

tb_path_x_simple.v
// =============================================================================
// tb_path_x_simple.v — Standalone Path X demonstration
//
// Mirrors the verified Path X RF result (0/32 bit errors over RF) using
// only qpsk_mod + qpsk_demod.  This is the QPSK ↔ frequency-bin core
// of the OFDM modem: it shows that bits → QPSK → loopback → QPSK demod
// recovers TEST_BITS_LO = 0x0F0F0F0F exactly, byte-for-byte.
//
// In Path X (Python over RF) the round trip is:
//   bits → QPSK constellation → IFFT → CP → DAC → AD9363 → SMA loop →
//   AD9363 → CP-strip → FFT → demap → QPSK hard-decision → bits
//
// IFFT+FFT, CP, AD9363 all cancel for ideal samples — the math that
// matters is QPSK → loopback → QPSK demod.  This TB demonstrates that
// math passes 0/32 bits, identical to the RF observation.
//
// Run on build server (Vivado 2024.2):
//   cd path_x_sim && \
//   xvlog tb_path_x_simple.v qpsk_mod.v qpsk_demod.v && \
//   xelab tb_path_x_simple -snapshot path_x && \
//   xsim path_x -tclbatch run.tcl
// =============================================================================
`timescale 1ns/1ps

module tb_path_x_simple;

parameter CLK_PERIOD = 10;
parameter [31:0] TEST_BITS_LO = 32'h0F0F0F0F;

reg clk = 0;
reg rst_n = 0;
always #(CLK_PERIOD/2) clk = ~clk;

// QPSK modulator (TX side)
reg  [1:0]  bits_in;
reg         valid_in;
wire [15:0] tx_I, tx_Q;
wire        tx_valid;

qpsk_mod u_qpsk_mod (
    .clk      (clk),
    .rst_n    (rst_n),
    .bits_in  (bits_in),
    .valid_in (valid_in),
    .I_out    (tx_I),
    .Q_out    (tx_Q),
    .valid_out(tx_valid)
);

// QPSK demodulator (RX side)
// qpsk_demod ports:  (clk, rst_n, I_in, Q_in, valid_in, llr0_out, llr1_out, valid_out)
reg  [15:0] rx_I, rx_Q;
reg         rx_valid_in;
wire [7:0]  llr0, llr1;
wire        rx_valid_out;

qpsk_demod u_qpsk_demod (
    .clk       (clk),
    .rst_n     (rst_n),
    .I_in      (rx_I),
    .Q_in      (rx_Q),
    .valid_in  (rx_valid_in),
    .llr0      (llr0),
    .llr1      (llr1),
    .valid_out (rx_valid_out)
);

// Capture decoded bits
integer  bit_idx;
reg [31:0] decoded;
reg        capture_active;

// Loopback path: tx_valid → rx side, with one cycle latency
always @(posedge clk) begin
    rx_I        <= tx_I;
    rx_Q        <= tx_Q;
    rx_valid_in <= tx_valid;
end

// Capture LLR hard-decisions into decoded
always @(posedge clk) begin
    if (!rst_n) begin
        decoded <= 32'h0;
        bit_idx <= 0;
    end else if (rx_valid_out && capture_active && bit_idx < 32) begin
        // qpsk_demod: llr0=I-axis bit (bits_in[0]), llr1=Q-axis bit (bits_in[1])
        // Mapping: I positive → bit=0, I negative → bit=1
        // llr0 sign: positive llr → bit=0
        decoded[bit_idx]   <= ($signed(llr0) < 0) ? 1'b1 : 1'b0;
        decoded[bit_idx+1] <= ($signed(llr1) < 0) ? 1'b1 : 1'b0;
        bit_idx <= bit_idx + 2;
    end
end

initial begin
    $dumpfile("path_x_simple.vcd");
    $dumpvars(0, tb_path_x_simple);
end

integer i, errors;

initial begin
    $display("==============================================================");
    $display("  Path X simulation (simple) — QPSK modem core");
    $display("  Mirrors RF result: TEST_BITS[31:0]=0x%08X", TEST_BITS_LO);
    $display("==============================================================");

    bits_in        = 2'b0;
    valid_in       = 0;
    rx_I           = 0;
    rx_Q           = 0;
    rx_valid_in    = 0;
    capture_active = 0;

    repeat (10) @(posedge clk);
    rst_n = 1;
    repeat (5) @(posedge clk);

    // Begin capturing demod output
    capture_active = 1;

    // Stream 16 QPSK pairs = 32 bits of TEST_BITS_LO
    @(posedge clk);
    for (i = 0; i < 16; i = i + 1) begin
        bits_in  = {TEST_BITS_LO[2*i+1], TEST_BITS_LO[2*i]};
        valid_in = 1;
        @(posedge clk);
    end
    valid_in = 0;
    bits_in  = 2'b0;

    // Wait for last RX samples to flush
    repeat (20) @(posedge clk);

    // ----- Verify -----
    errors = 0;
    for (i = 0; i < 32; i = i + 1) begin
        if (decoded[i] !== TEST_BITS_LO[i]) begin
            errors = errors + 1;
        end
    end

    $display("--------------------------------------------------------------");
    $display("  TX  bits[31:0] = 0x%08X", TEST_BITS_LO);
    $display("  RX  bits[31:0] = 0x%08X", decoded);
    $display("  bit errors     = %0d / 32", errors);
    if (errors == 0)
        $display("  *** PASS *** Path X QPSK core matches RF (0/32 errors).");
    else
        $display("  *** FAIL *** %0d bit errors", errors);
    $display("==============================================================");

    repeat (20) @(posedge clk);
    $finish;
end

initial begin
    #20000;
    $display("WATCHDOG TIMEOUT");
    $finish;
end

endmodule

path_x_simple.vcd
$date
   Wed May  6 22:55:49 2026
$end

$version
  2024.2.0
  $dumpfile ("path_x_simple.vcd") 
$end

$timescale
  1ps
$end

$scope module tb_path_x_simple $end
$var reg 1 ! clk $end
$var reg 1 " rst_n $end
$var reg 2 # bits_in [1:0] $end
$var reg 1 $ valid_in $end
$var wire 16 % tx_I [15:0] $end
$var wire 16 & tx_Q [15:0] $end
$var wire 1 ' tx_valid $end
$var reg 16 ( rx_I [15:0] $end
$var reg 16 ) rx_Q [15:0] $end
$var reg 1 * rx_valid_in $end
$var wire 8 + llr0 [7:0] $end
$var wire 8 , llr1 [7:0] $end
$var wire 1 - rx_valid_out $end
$var integer 32 . bit_idx [31:0] $end
$var reg 32 / decoded [31:0] $end
$var reg 1 0 capture_active $end
$var integer 32 1 i [31:0] $end
$var integer 32 2 errors [31:0] $end
$scope module u_qpsk_mod $end
$var wire 1 3 clk $end
$var wire 1 4 rst_n $end
$var wire 2 5 bits_in [1:0] $end
$var wire 1 6 valid_in $end
$var reg 16 7 I_out [15:0] $end
$var reg 16 8 Q_out [15:0] $end
$var reg 1 9 valid_out $end
$upscope $end
$scope module u_qpsk_demod $end
$var wire 1 : clk $end
$var wire 1 ; rst_n $end
$var wire 16 < I_in [15:0] $end
$var wire 16 = Q_in [15:0] $end
$var wire 1 > valid_in $end
$var reg 8 ? llr0 [7:0] $end
$var reg 8 @ llr1 [7:0] $end
$var reg 1 A valid_out $end
$var wire 16 B I_s [15:0] $end
$var wire 16 C Q_s [15:0] $end
$var wire 16 D I_sh [15:0] $end
$var wire 16 E Q_sh [15:0] $end
$scope function sat8 $end
$var reg 8 F sat8 [7:0] $end
$var reg 16 G x [15:0] $end
$upscope $end
$upscope $end
$upscope $end
$enddefinitions $end

#0
$dumpvars
0!
0"
b0 #
0$
b0 %
b0 &
0'
b0 (
b0 )
0*
b0 +
b0 ,
0-
bx .
bx /
00
bx 1
bx 2
03
04
b0 5
06
b0 7
b0 8
09
0:
0;
b0 <
b0 =
0>
b0 ?
b0 @
0A
b0 B
b0 C
b0 D
b0 E
bx F
bx G
$end

#5000
1!
b0 .
b0 /
13
1:

#10000
0!
03
0:

#15000
1!
13
1:

#20000
0!
03
0:

#25000
1!
13
1:

#30000
0!
03
0:

#35000
1!
13
1:

#40000
0!
03
0:

#45000
1!
13
1:

#50000
0!
03
0:

#55000
1!
13
1:

#60000
0!
03
0:

#65000
1!
13
1:

#70000
0!
03
0:

#75000
1!
13
1:

#80000
0!
03
0:

#85000
1!
13
1:

#90000
0!
03
0:

#95000
1!
1"
13
14
1:
1;

#100000
0!
03
0:

#105000
1!
13
1:

#110000
0!
03
0:

#115000
1!
13
1:

#120000
0!
03
0:

#125000
1!
13
1:

#130000
0!
03
0:

#135000
1!
13
1:

#140000
0!
03
0:

#145000
1!
10
13
1:

#150000
0!
03
0:

#155000
1!
b11 #
1$
b1110100101011111 %
b1110100101011111 &
1'
b0 1
13
b11 5
16
b1110100101011111 7
b1110100101011111 8
19
1:

#160000
0!
03
0:

#165000
1!
b1110100101011111 (
b1110100101011111 )
1*
b1 1
13
1:
b1110100101011111 <
b1110100101011111 =
1>
b1110100101011111 B
b1110100101011111 C
b1111111111010010 D
b1111111111010010 E

#170000
0!
03
0:

#175000
1!
b0 #
b1011010100001 %
b1011010100001 &
b11010010 +
b11010010 ,
1-
b10 1
13
b0 5
b1011010100001 7
b1011010100001 8
1:
b11010010 ?
b11010010 @
1A
b11010010 F
b1111111111010010 G

#180000
0!
03
0:

#185000
1!
b1011010100001 (
b1011010100001 )
b10 .
b11 /
b11 1
13
1:
b1011010100001 <
b1011010100001 =
b1011010100001 B
b1011010100001 C
b101101 D
b101101 E

#190000
0!
03
0:

#195000
1!
b11 #
b1110100101011111 %
b1110100101011111 &
b101101 +
b101101 ,
b100 .
b1111 /
b100 1
13
b11 5
b1110100101011111 7
b1110100101011111 8
1:
b101101 ?
b101101 @
b101101 F
b101101 G

#200000
0!
03
0:

#205000
1!
b1110100101011111 (
b1110100101011111 )
b110 .
b101 1
13
1:
b1110100101011111 <
b1110100101011111 =
b1110100101011111 B
b1110100101011111 C
b1111111111010010 D
b1111111111010010 E

#210000
0!
03
0:

#215000
1!
b0 #
b1011010100001 %
b1011010100001 &
b11010010 +
b11010010 ,
b1000 .
b110 1
13
b0 5
b1011010100001 7
b1011010100001 8
1:
b11010010 ?
b11010010 @
b11010010 F
b1111111111010010 G

#220000
0!
03
0:

#225000
1!
b1011010100001 (
b1011010100001 )
b1010 .
b1100001111 /
b111 1
13
1:
b1011010100001 <
b1011010100001 =
b1011010100001 B
b1011010100001 C
b101101 D
b101101 E

#230000
0!
03
0:

#235000
1!
b11 #
b1110100101011111 %
b1110100101011111 &
b101101 +
b101101 ,
b1100 .
b111100001111 /
b1000 1
13
b11 5
b1110100101011111 7
b1110100101011111 8
1:
b101101 ?
b101101 @
b101101 F
b101101 G

#240000
0!
03
0:

#245000
1!
b1110100101011111 (
b1110100101011111 )
b1110 .
b1001 1
13
1:
b1110100101011111 <
b1110100101011111 =
b1110100101011111 B
b1110100101011111 C
b1111111111010010 D
b1111111111010010 E

#250000
0!
03
0:

#255000
1!
b0 #
b1011010100001 %
b1011010100001 &
b11010010 +
b11010010 ,
b10000 .
b1010 1
13
b0 5
b1011010100001 7
b1011010100001 8
1:
b11010010 ?
b11010010 @
b11010010 F
b1111111111010010 G

#260000
0!
03
0:

#265000
1!
b1011010100001 (
b1011010100001 )
b10010 .
b110000111100001111 /
b1011 1
13
1:
b1011010100001 <
b1011010100001 =
b1011010100001 B
b1011010100001 C
b101101 D
b101101 E

#270000
0!
03
0:

#275000
1!
b11 #
b1110100101011111 %
b1110100101011111 &
b101101 +
b101101 ,
b10100 .
b11110000111100001111 /
b1100 1
13
b11 5
b1110100101011111 7
b1110100101011111 8
1:
b101101 ?
b101101 @
b101101 F
b101101 G

#280000
0!
03
0:

#285000
1!
b1110100101011111 (
b1110100101011111 )
b10110 .
b1101 1
13
1:
b1110100101011111 <
b1110100101011111 =
b1110100101011111 B
b1110100101011111 C
b1111111111010010 D
b1111111111010010 E

#290000
0!
03
0:

#295000
1!
b0 #
b1011010100001 %
b1011010100001 &
b11010010 +
b11010010 ,
b11000 .
b1110 1
13
b0 5
b1011010100001 7
b1011010100001 8
1:
b11010010 ?
b11010010 @
b11010010 F
b1111111111010010 G

#300000
0!
03
0:

#305000
1!
b1011010100001 (
b1011010100001 )
b11010 .
b11000011110000111100001111 /
b1111 1
13
1:
b1011010100001 <
b1011010100001 =
b1011010100001 B
b1011010100001 C
b101101 D
b101101 E

#310000
0!
03
0:

#315000
1!
0$
0'
b101101 +
b101101 ,
b11100 .
b1111000011110000111100001111 /
b10000 1
13
06
09
1:
b101101 ?
b101101 @
b101101 F
b101101 G

#320000
0!
03
0:

#325000
1!
0*
b11110 .
13
1:
0>

#330000
0!
03
0:

#335000
1!
0-
b100000 .
13
1:
0A

#340000
0!
03
0:

#345000
1!
13
1:

#350000
0!
03
0:

#355000
1!
13
1:

#360000
0!
03
0:

#365000
1!
13
1:

#370000
0!
03
0:

#375000
1!
13
1:

#380000
0!
03
0:

#385000
1!
13
1:

#390000
0!
03
0:

#395000
1!
13
1:

#400000
0!
03
0:

#405000
1!
13
1:

#410000
0!
03
0:

#415000
1!
13
1:

#420000
0!
03
0:

#425000
1!
13
1:

#430000
0!
03
0:

#435000
1!
13
1:

#440000
0!
03
0:

#445000
1!
13
1:

#450000
0!
03
0:

#455000
1!
13
1:

#460000
0!
03
0:

#465000
1!
13
1:

#470000
0!
03
0:

#475000
1!
13
1:

#480000
0!
03
0:

#485000
1!
13
1:

#490000
0!
03
0:

#495000
1!
13
1:

#500000
0!
03
0:

#505000
1!
13
1:

#510000
0!
03
0:

#515000
1!
b100000 1
b0 2
13
1:

